krx/__init__.py
krx/parser.py
krx_rigger-0.0.34.dist-info/LICENSE
krx_rigger-0.0.34.dist-info/METADATA
krx_rigger-0.0.34.dist-info/WHEEL
krx_rigger-0.0.34.dist-info/top_level.txt
krx_rigger-0.0.34.dist-info/RECORD
