Metadata-Version: 2.1
Name: krx-rigger
Version: 0.0.34
Summary: krx web crawler wrapper
Home-page: https://github.com/cheddars/krx_rigger
Author: cheddars
Author-email: nezahrish@gmail.com
License: MIT
Platform: UNKNOWN
Classifier: Programming Language :: Python :: 3
Classifier: License :: OSI Approved :: MIT License
Classifier: Operating System :: OS Independent
License-File: LICENSE
Requires-Dist: requests
Requires-Dist: bs4
Requires-Dist: adt-cache (==0.0.14)
